piptv_pmg/__init__.py
piptv_pmg/pmg.py
piptv_pmg-0.2.0.dist-info/LICENSE
piptv_pmg-0.2.0.dist-info/METADATA
piptv_pmg-0.2.0.dist-info/WHEEL
piptv_pmg-0.2.0.dist-info/top_level.txt
piptv_pmg-0.2.0.dist-info/RECORD
