Metadata-Version: 2.1
Name: piptv-pmg
Version: 0.2.0
Summary: Piptv M3U Generator - An M3U IPTV playlist generator using piptvs scraping logic
Home-page: https://github.com/schwifty42069/pmg
Author: Brett Hufnagle
Author-email: teachingchain0420@gmail.com
License: UNKNOWN
Platform: UNKNOWN
Classifier: Programming Language :: Python :: 3
Classifier: License :: OSI Approved :: MIT License
Classifier: Operating System :: OS Independent
Requires-Python: >=3.6
Requires-Dist: setuptools (==41.2.0)
Requires-Dist: requests (==2.22.0)
Requires-Dist: beautifulsoup4 (==4.8.1)
